kube_kombu/__init__.py
kube_kombu/abstract_consumer_adapter.py
kube_kombu/consumer.py
kube_kombu/consumer_config.py
kube_kombu/healthcheck_server.py
kube_kombu/start_consumer.py
kube_kombu/worker.py
kube_kombu-1.0.6.dist-info/LICENSE
kube_kombu-1.0.6.dist-info/METADATA
kube_kombu-1.0.6.dist-info/WHEEL
kube_kombu-1.0.6.dist-info/top_level.txt
kube_kombu-1.0.6.dist-info/RECORD
