Metadata-Version: 2.1
Name: kube-kombu
Version: 1.0.6
Summary: Running kombu consumers with support of liveness probe for kubernetes
Home-page: https://github.com/Anmol-Porwal18/kube_kombu
Author: Anmol Porwal
Author-email: anmolporwal@ymail.com
License: MIT
Keywords: kubernetes,kombu,consumer,liveness probe
Platform: any
Classifier: Programming Language :: Python :: 3.7
Classifier: License :: OSI Approved :: MIT License
Classifier: Operating System :: OS Independent
Requires-Python: >=3.7
License-File: LICENSE
Requires-Dist: kombu (==5.2.3)
